oneNeuron/__init__.py
oneNeuron/perceptron.py
one_neuron_pypi_sandeep3119-0.0.2.dist-info/LICENSE
one_neuron_pypi_sandeep3119-0.0.2.dist-info/METADATA
one_neuron_pypi_sandeep3119-0.0.2.dist-info/WHEEL
one_neuron_pypi_sandeep3119-0.0.2.dist-info/top_level.txt
one_neuron_pypi_sandeep3119-0.0.2.dist-info/RECORD
